happy_templates/__init__.py
happy_templates/tags.py
happy_templates-0.0.0.dist-info/METADATA
happy_templates-0.0.0.dist-info/WHEEL
happy_templates-0.0.0.dist-info/RECORD
