Metadata-Version: 2.3
Name: happy-templates
Version: 0.0.0
Summary: The most Pythonic HTML.
Project-URL: Homepage, https://github.com/Zimzozaur/happy-templates
Project-URL: Issues, https://github.com/Zimzozaur/happy-templates/issues
Author-email: Simon Piechutowski <szymonpiechutowski@gmail.com>
Classifier: Development Status :: 1 - Planning
Classifier: Intended Audience :: Developers
Classifier: License :: OSI Approved :: MIT License
Classifier: Operating System :: MacOS
Classifier: Operating System :: Microsoft :: Windows :: Windows 10
Classifier: Operating System :: Microsoft :: Windows :: Windows 11
Classifier: Operating System :: POSIX :: Linux
Classifier: Programming Language :: Python :: 3.12
Classifier: Typing :: Typed
Requires-Python: >=3.12
Provides-Extra: dev
Requires-Dist: pre-commit~=4.0.1; extra == 'dev'
Requires-Dist: pytest~=8.3.2; extra == 'dev'
Requires-Dist: ruff>=0.6.1; extra == 'dev'
